setup.py
typographie/__init__.py
typographie/models.py
typographie/tests.py
typographie.egg-info/PKG-INFO
typographie.egg-info/SOURCES.txt
typographie.egg-info/dependency_links.txt
typographie.egg-info/top_level.txt
typographie.egg-info/zip-safe
typographie/templatetags/__init__.py
typographie/templatetags/smartypants.py
typographie/templatetags/typographie.py