Metadata-Version: 1.0
Name: typographie
Version: 0.0.1
Summary: Apply french typografy rules
Home-page: https://github.com/oxys-net/django-typographie
Author: OXYS.net
Author-email: UNKNOWN
License: UNKNOWN
Keywords: django typogrify french français règles typographiques
Platform: UNKNOWN
Classifier: Intended Audience :: Developers
Classifier: Natural Language :: English
Classifier: Operating System :: OS Independent
Classifier: Programming Language :: Python
